{"name": "rate_scenario", "arguments": {"com_port": "The port of nuttcp server for signalling", "port": "The port of the server", "ntimes": "The number of tests to perform", "tcp_eq_time": "The elasped time after which we begin to consider the rate measures for TCP mean calculation", "dst_ip": "The IP of the server", "duration": "The duration of each test (sec.)"}, "openbach_functions": [{"wait": {"time": 1, "launched_ids": [], "finished_ids": []}, "start_job_instance": {"entity_name": "ST", "iperf3": {"exit": true, "num_flows": 2, "port": "$port", "rate_compute_time": "$tcp_eq_time", "iterations": "$ntimes", "server_mode": true}, "offset": 0}, "id": 0}, {"wait": {"time": 2, "launched_ids": [0], "finished_ids": []}, "start_job_instance": {"entity_name": "Gateway", "iperf3": {"tos": "0x28", "num_flows": 2, "iterations": "$ntimes", "server_mode": false, "time": "$duration", "port": "$port", "client_mode_server_ip": "$dst_ip", "mss": 960}, "offset": 0}, "id": 1}, {"wait": {"time": 2, "launched_ids": [], "finished_ids": [1, 0]}, "start_job_instance": {"entity_name": "ST", "nuttcp": {"command_port": "$com_port", "server_mode": true}, "offset": 0}, "id": 2}, {"wait": {"time": 2, "launched_ids": [2], "finished_ids": []}, "start_job_instance": {"entity_name": "Gateway", "nuttcp": {"dscp": "0x28", "receiver": false, "iterations": "$ntimes", "server_mode": false, "command_port": "$com_port", "port": "$port", "rate_compute_time": "$tcp_eq_time", "server_ip": "$dst_ip", "n_streams": 2, "mss": 960, "duration": "$duration"}, "offset": 0}, "id": 3}, {"wait": {"time": 0, "launched_ids": [], "finished_ids": [3]}, "id": 4, "stop_job_instances": {"openbach_function_ids": [2]}}], "description": "rate_scenario", "constants": {}}